{
	"version": 1,
	"info": {
		"ID": "1796",
		"성별": "남",
		"나이": 11,
		"학년": "고학년",
		"유형구분": "일반아동",
		"가정환경": "일반(핵가족 이상)",
		"상담일자": "2023-10-29",
		"평가일시": "2023-10-29",
		"작성자(상담사)": "임상심리사 2급",
		"상호작용 특성(종합)": "협조적",
		"긴장 수준(종합)": "보통",
		"행동 특성(종합)": "||",
		"위기단계": "학대의심",
		"합계점수": 99,
		"학대의심": "신체학대",
		"행동특성 점수": 0,
		"임상가 종합소견": "해당 아동은 심리적 원인과 관련된 통증 호소와 더불어 학대로 인한 신체손상 가능성이 있습니다. 지속적인 스트레스 상황으로 즐거움을 경험하지 못하며, 분노가 지속되고 있습니다. 또한, 심리적인 요인으로 인해 깊은 잠에 들지 못하는 것으로 보입니다. 부모님에게 무서움과 두려움을 경험하고 있으며, 부모님의 차별로 인해 일부 형제에게 불편감을 느끼는 것으로 나타나고 있습니다. 친구와 교사와의 관계는 원만한 것으로 보입니다. 과도한 스트레스와 환경적 요인으로 불행감으로 미래에 대한 희망이 부재합니다. 또한, 방임, 정서학대, 신체학대가 의심되어 적극적인 개입이 필요한 상태입니다. 성학대의 징후는 유추되지 않았습니다. 해당 아동이 외상의 경험을 자주 떠올려 심리적인 개입이 필요합니다. 종합하면, 아동은 '응급위기'로 판단되어 즉각적인 개입 및 대처가 필요합니다."
	},
	"list": [
		{
			"문항": "신체적 불편감",
			"문항합계": 14,
			"위기단계": "상담필요",
			"list": [
				{
					"항목": "통증",
					"임상가코멘트": {
						"val": "④ 통증이 심리적 원인과 관련되어 있을 가능성이 높습니다. [7점]"
					},
					"점수": 7,
					"문제요인": {
						"val": "있음"
					},
					"부위": {
						"val": "||두통||"
					},
					"빈도": {
						"val": "||자주(주 2~3회)||"
					},
					"기간": {
						"val": "||한 달 이상||"
					},
					"audio": [
						{
							"type": "Q",
							"text": "최근에 건강한가요? 혹시 아픈 곳이 있나요?",
							"wave": "all.wav",
							"start": "00:02.191",
							"end": "00:05.324"
						},
						{
							"type": "A",
							"text": "두통이 있어요.",
							"wave": "all.wav",
							"start": "00:06.541",
							"end": "00:07.994"
						},
						{
							"type": "Q",
							"text": "언제부터 아팠어요? 일주일에 몇 번이나 아픈 거 같아요?",
							"wave": "all.wav",
							"start": "00:09.114",
							"end": "00:12.972"
						},
						{
							"type": "A",
							"text": "한 달 넘었어요. 매일 아파요.",
							"wave": "all.wav",
							"start": "00:14.134",
							"end": "00:16.222"
						},
						{
							"type": "Q",
							"text": "아팠던 이유가 있을까요?",
							"wave": "all.wav",
							"start": "00:17.301",
							"end": "00:19.458"
						},
						{
							"type": "A",
							"text": "아무래도 새엄마랑 누나 때문에 스트레스받아서 아픈 거 같아요.",
							"wave": "all.wav",
							"start": "00:20.482",
							"end": "00:24.769"
						},
						{
							"type": "Q",
							"text": "해당 부위가 원래 자주 아팠어요?",
							"wave": "all.wav",
							"start": "00:25.931",
							"end": "00:28.185"
						},
						{
							"type": "A",
							"text": "아니요. 안 아팠어요.",
							"wave": "all.wav",
							"start": "00:29.471",
							"end": "00:31.407"
						}
					]
				},
				{
					"항목": "신체손상",
					"임상가코멘트": {
						"val": "⑤ 학대 가능성이 있습니다. [7점]"
					},
					"점수": 7,
					"문제요인": {
						"val": "있음"
					},
					"손상정도": {
						"val": "심한 손상"
					},
					"손상요인": {
						"val": "타인에 의한 의도적 손상"
					},
					"audio": [
						{
							"type": "Q",
							"text": "최근에 다쳤던 적이 있나요? 다쳤다면 어디를 다쳤나요?",
							"wave": "all.wav",
							"start": "00:32.569",
							"end": "00:36.607"
						},
						{
							"type": "A",
							"text": "네, 아빠한테 맞아서 엉덩이를 다쳤어요.",
							"wave": "all.wav",
							"start": "00:37.769",
							"end": "00:40.756"
						},
						{
							"type": "Q",
							"text": "언제 다쳤나요?",
							"wave": "all.wav",
							"start": "00:41.973",
							"end": "00:43.370"
						},
						{
							"type": "A",
							"text": "저번 주에 다쳤어요.",
							"wave": "all.wav",
							"start": "00:44.490",
							"end": "00:46.219"
						},
						{
							"type": "Q",
							"text": "병원에서 치료받았나요?",
							"wave": "all.wav",
							"start": "00:47.547",
							"end": "00:49.552"
						},
						{
							"type": "A",
							"text": "네, 학교 선생님이 의자에 왜 못 앉냐고 잠깐 봐도 되냐고 하더니 병원에 데려갔어요. 꼬리뼈 골절이 의심된다고 해서 꽤 오래 병원을 다녀야 한대요.",
							"wave": "all.wav",
							"start": "00:50.658",
							"end": "01:00.823"
						}
					]
				}
			]
		},
		{
			"문항": "기분문제",
			"문항합계": 12,
			"위기단계": "상담필요",
			"list": [
				{
					"항목": "즐거움",
					"임상가코멘트": {
						"val": "④ 지속적인 스트레스 상황이나 우울감으로 즐거움을 경험하지 못하는 것일 수 있습니다. [7점]"
					},
					"점수": 7,
					"문제요인": {
						"val": "있음"
					},
					"지속시간": {
						"val": "1년 이상"
					},
					"audio": [
						{
							"type": "Q",
							"text": "무엇을 할 때가 즐거워요?",
							"wave": "all.wav",
							"start": "01:02.040",
							"end": "01:04.004"
						},
						{
							"type": "A",
							"text": "즐겁지 않아요.",
							"wave": "all.wav",
							"start": "01:05.346",
							"end": "01:06.549"
						},
						{
							"type": "Q",
							"text": "언제부터 즐겁지 못하다고 느꼈어요?",
							"wave": "all.wav",
							"start": "01:07.807",
							"end": "01:10.421"
						},
						{
							"type": "A",
							"text": "아빠가 재혼한 다음부터요. 1년 됐어요.",
							"wave": "all.wav",
							"start": "01:11.541",
							"end": "01:14.542"
						}
					]
				},
				{
					"항목": "분노/짜증",
					"임상가코멘트": {
						"val": "③ 분노와 짜증을 경험하나 대처기술이 없거나 부적절한 대처기술을 가지고 있습니다. [5점]"
					},
					"점수": 5,
					"문제요인": {
						"val": "||분노||"
					},
					"대처기술": {
						"val": "없음"
					},
					"audio": [
						{
							"type": "Q",
							"text": "최근 일주일 동안 짜증이나 화가 난 적이 있나요?",
							"wave": "all.wav",
							"start": "01:15.939",
							"end": "01:19.466"
						},
						{
							"type": "A",
							"text": "네, 아빠한테 맞아서 화가 났어요.",
							"wave": "all.wav",
							"start": "01:20.572",
							"end": "01:23.297"
						},
						{
							"type": "Q",
							"text": "그런 일이 자주 일어나요?",
							"wave": "all.wav",
							"start": "01:24.514",
							"end": "01:26.394"
						},
						{
							"type": "A",
							"text": "네, 툭하면 야구방망이로 엉덩이를 때려요. 일주일에 한 번 이상 그래요.",
							"wave": "all.wav",
							"start": "01:27.515",
							"end": "01:32.452"
						},
						{
							"type": "Q",
							"text": "평소 짜증이나 화가 날 때, 어떻게 하면 마음이 풀려요?",
							"wave": "all.wav",
							"start": "01:33.669",
							"end": "01:37.583"
						},
						{
							"type": "A",
							"text": "아빠가 안 듣는 곳에서 아빠를 저주하고 욕해요. 그래도 화가 안 풀려요.",
							"wave": "all.wav",
							"start": "01:38.786",
							"end": "01:43.474"
						}
					]
				}
			]
		},
		{
			"문항": "자율신경계",
			"문항합계": 7,
			"위기단계": "상담필요",
			"list": [
				{
					"항목": "수면",
					"임상가코멘트": {
						"val": "③ 심리적 요인으로 깊은 잠에 들기 어려운 것으로 보입니다. [7점]"
					},
					"점수": 7,
					"수면시간": {
						"val": "6"
					},
					"문제요인": {
						"val": "있음"
					},
					"수면문제": {
						"val": "||불면(자주 깸)||"
					},
					"audio": [
						{
							"type": "Q",
							"text": "평소 몇 시에 자서 몇 시에 일어나요?",
							"wave": "all.wav",
							"start": "01:44.581",
							"end": "01:47.028"
						},
						{
							"type": "A",
							"text": "한 시에 누워서 일곱 시에 일어나요.",
							"wave": "all.wav",
							"start": "01:48.245",
							"end": "01:50.887"
						},
						{
							"type": "Q",
							"text": "아침에 일어났을 때, 몸 상태는 어때요?",
							"wave": "all.wav",
							"start": "01:52.118",
							"end": "01:55.188"
						},
						{
							"type": "A",
							"text": "괜찮은 거 같아요.",
							"wave": "all.wav",
							"start": "01:56.391",
							"end": "01:57.802"
						},
						{
							"type": "Q",
							"text": "평소에 잠들기 힘들거나, 잠자는 중간에 자주 깨요?",
							"wave": "all.wav",
							"start": "01:58.936",
							"end": "02:02.822"
						},
						{
							"type": "A",
							"text": "네, 자주 깨요.",
							"wave": "all.wav",
							"start": "02:04.053",
							"end": "02:05.643"
						}
					]
				}
			]
		},
		{
			"문항": "대인관계",
			"문항합계": 15,
			"위기단계": "상담필요",
			"list": [
				{
					"항목": "아버지",
					"임상가코멘트": {
						"val": "④ 기타",
						"기타": "공포, 두려움과 더불어 혐오/무시의 감정을 경험하고 있습니다. [6점]"
					},
					"점수": 6,
					"아버지": {
						"val": "자기중심성(분노)"
					},
					"대상자": {
						"val": "(해당 없음)"
					},
					"관계": {
						"val": "(해당 없음)"
					},
					"차별": {
						"val": "(해당 없음)"
					},
					"audio": [
						{
							"type": "Q",
							"text": "평소 아빠는 어떤 표정을 자주 짓나요?",
							"wave": "all.wav",
							"start": "02:06.833",
							"end": "02:09.571"
						},
						{
							"type": "A",
							"text": "항상 화난 표정이요. 기분 나쁜 특유의 표정이 있어요.",
							"wave": "all.wav",
							"start": "02:10.981",
							"end": "02:15.200"
						},
						{
							"type": "Q",
							"text": "아빠가 왜 항상 그런 표정인 거 같아요?",
							"wave": "all.wav",
							"start": "02:16.472",
							"end": "02:19.252"
						},
						{
							"type": "A",
							"text": "성격이 더러워서요.",
							"wave": "all.wav",
							"start": "02:20.690",
							"end": "02:22.253"
						},
						{
							"type": "Q",
							"text": "아빠가 그런 표정을 지으실 때, 내 기분은 어때요?",
							"wave": "all.wav",
							"start": "02:23.774",
							"end": "02:27.301"
						},
						{
							"type": "A",
							"text": "무서워요. 반항심이 들다가도 못 이길 거 아니까 더 무서워요.",
							"wave": "all.wav",
							"start": "02:28.628",
							"end": "02:33.095"
						}
					]
				},
				{
					"항목": "어머니",
					"임상가코멘트": {
						"val": "④ 기타",
						"기타": "공포, 두려움과 더불어 혐오/무시의 감정을 경험하고 있습니다. [6점]"
					},
					"점수": 6,
					"어머니": {
						"val": "자기중심성(분노)"
					},
					"대상자": {
						"val": "(해당 없음)"
					},
					"관계": {
						"val": "(해당 없음)"
					},
					"차별": {
						"val": "(해당 없음)"
					},
					"audio": [
						{
							"type": "Q",
							"text": "평소 새엄마는 어떤 표정을 자주 짓나요?",
							"wave": "all.wav",
							"start": "02:34.492",
							"end": "02:37.410"
						},
						{
							"type": "A",
							"text": "새엄마도 무서운 표정을 지어요.",
							"wave": "all.wav",
							"start": "02:38.779",
							"end": "02:41.006"
						},
						{
							"type": "Q",
							"text": "새엄마가 그런 표정을 짓는 이유는 뭐라고 생각해요?",
							"wave": "all.wav",
							"start": "02:42.320",
							"end": "02:45.846"
						},
						{
							"type": "A",
							"text": "누나만 키우고 싶은데, 저랑 형이 있어서 싫은 거 같아요.",
							"wave": "all.wav",
							"start": "02:47.160",
							"end": "02:50.701"
						},
						{
							"type": "Q",
							"text": "엄마가 그런 표정을 지을 때 어떤 기분이 들어요?",
							"wave": "all.wav",
							"start": "02:52.083",
							"end": "02:55.389"
						},
						{
							"type": "A",
							"text": "무서워요. 때로는 죽여버리고 싶어요.",
							"wave": "all.wav",
							"start": "02:56.620",
							"end": "02:59.469"
						}
					]
				},
				{
					"항목": "기타 보호자",
					"임상가코멘트": {
						"val": ""
					},
					"점수": 0,
					"기타보호자명": {
						"이름입력": "",
						"val": "(해당 없음)"
					},
					"대상자": {
						"val": "누나/언니"
					},
					"관계": {
						"val": "냉담"
					},
					"차별": {
						"val": "다른 형제자매를 편애함"
					},
					"audio": [
						{
							"type": "Q",
							"text": "혹시 부모님 말고 나를 돌봐주는 어른이 있나요?",
							"wave": "all.wav",
							"start": "03:00.727",
							"end": "03:04.392"
						},
						{
							"type": "A",
							"text": "아니요. 없어요.",
							"wave": "all.wav",
							"start": "03:05.664",
							"end": "03:07.075"
						}
					]
				},
				{
					"항목": "형제자매",
					"임상가코멘트": {
						"val": "⑤ 기타",
						"기타": "부모님으로부터 일부 형제와의 차별을 경험하고 있으며, 냉담한 관계를 보이고 있습니다. [3점]"
					},
					"점수": 3,
					"인원": {
						"val": "2"
					},
					"대상자": {
						"val": "형/오빠"
					},
					"관계": {
						"val": "우호적"
					},
					"차별": {
						"val": "없음"
					},
					"audio": [
						{
							"type": "Q",
							"text": "혹시, 형제자매가 있나요?",
							"wave": "all.wav",
							"start": "03:08.320",
							"end": "03:10.436"
						},
						{
							"type": "A",
							"text": "네, 새엄마가 데려온 누나 한 명이랑 제 친형 한 명이 있어요.",
							"wave": "all.wav",
							"start": "03:11.528",
							"end": "03:15.912"
						},
						{
							"type": "Q",
							"text": "누나랑은 사이가 어때요?",
							"wave": "all.wav",
							"start": "03:17.364",
							"end": "03:19.342"
						},
						{
							"type": "A",
							"text": "안 좋아요. 서로 관심도 없고 말도 안 섞어요.",
							"wave": "all.wav",
							"start": "03:20.780",
							"end": "03:24.182"
						},
						{
							"type": "Q",
							"text": "평소 부모님이 누나랑 나를 차별하는 거 같나요?",
							"wave": "all.wav",
							"start": "03:25.372",
							"end": "03:28.801"
						},
						{
							"type": "A",
							"text": "네, 아빠도 그 누나만 이뻐해요. 새엄마는 물론이고요.",
							"wave": "all.wav",
							"start": "03:30.046",
							"end": "03:34.029"
						},
						{
							"type": "Q",
							"text": "형이랑은 사이가 어때요?",
							"wave": "all.wav",
							"start": "03:35.412",
							"end": "03:37.487"
						},
						{
							"type": "A",
							"text": "좋아요. 제가 형한테 의지를 많이 해요.",
							"wave": "all.wav",
							"start": "03:38.856",
							"end": "03:41.967"
						},
						{
							"type": "Q",
							"text": "평소 부모님이 형이랑 나를 차별하는 거 같나요?",
							"wave": "all.wav",
							"start": "03:43.267",
							"end": "03:46.462"
						},
						{
							"type": "A",
							"text": "아니요. 우리 둘 다 싫어하는 거 같아요.",
							"wave": "all.wav",
							"start": "03:47.817",
							"end": "03:50.016"
						}
					]
				},
				{
					"항목": "친구",
					"임상가코멘트": {
						"val": "① 교우관계과 원만한 것으로 보입니다. [0점]"
					},
					"점수": 0,
					"문제요인": {
						"val": "없음"
					},
					"교우관계": {
						"val": "(해당 없음)"
					},
					"audio": [
						{
							"type": "Q",
							"text": "친구들이랑은 주로 뭐 하고 놀아요?",
							"wave": "all.wav",
							"start": "03:51.275",
							"end": "03:53.750"
						},
						{
							"type": "A",
							"text": "축구하거나 피시방에서 게임을 해요.",
							"wave": "all.wav",
							"start": "03:54.801",
							"end": "03:57.747"
						},
						{
							"type": "Q",
							"text": "주로 몇 명이 같이 어울려요?",
							"wave": "all.wav",
							"start": "03:59.006",
							"end": "04:00.956"
						},
						{
							"type": "A",
							"text": "저까지 네 명이에요.",
							"wave": "all.wav",
							"start": "04:02.200",
							"end": "04:03.984"
						}
					]
				},
				{
					"항목": "교사",
					"임상가코멘트": {
						"val": "① 담임 선생님과의 관계가 원만한 것으로 보입니다 [0점]"
					},
					"점수": 0,
					"담임": {
						"val": "우호"
					},
					"audio": [
						{
							"type": "Q",
							"text": "담임선생님을 좋아해요, 아니면 싫어해요?",
							"wave": "all.wav",
							"start": "04:05.353",
							"end": "04:08.341"
						},
						{
							"type": "A",
							"text": "담임선생님 좋아요.",
							"wave": "all.wav",
							"start": "04:09.572",
							"end": "04:11.356"
						},
						{
							"type": "Q",
							"text": "담임선생님이 왜 좋아요?",
							"wave": "all.wav",
							"start": "04:12.559",
							"end": "04:14.440"
						},
						{
							"type": "A",
							"text": "칭찬도 많이 해주시고, 간식도 많이 주셔서 좋아요.",
							"wave": "all.wav",
							"start": "04:15.657",
							"end": "04:19.017"
						}
					]
				}
			]
		},
		{
			"문항": "기본생활",
			"문항합계": 20,
			"위기단계": "상담필요",
			"list": [
				{
					"항목": "걱정",
					"임상가코멘트": {
						"val": "④ 스트레스 수준이 높아 심리적 개입(상담 등)이 필요한 것으로 보입니다. [7점]"
					},
					"점수": 7,
					"내용": {
						"val": "가족"
					},
					"일상영향": {
						"val": "항상 힘듦 (주3일 이상)"
					},
					"audio": [
						{
							"type": "Q",
							"text": "요즘 가장 큰 걱정거리는 뭔가요?",
							"wave": "all.wav",
							"start": "04:20.303",
							"end": "04:23.014"
						},
						{
							"type": "A",
							"text": "가족이 걱정이에요.",
							"wave": "all.wav",
							"start": "04:24.314",
							"end": "04:25.932"
						},
						{
							"type": "Q",
							"text": "왜 가족이 걱정이에요?",
							"wave": "all.wav",
							"start": "04:27.080",
							"end": "04:28.975"
						},
						{
							"type": "A",
							"text": "집에 사는 게 지옥 같아요. 아빠가 자꾸 때리는 것도 욕하는 것도 지겨워요.",
							"wave": "all.wav",
							"start": "04:30.040",
							"end": "04:35.087"
						},
						{
							"type": "Q",
							"text": "그 걱정거리 때문에 생활이 좀 불편하거나 힘들어요? 얼마나 자주 그런가요?",
							"wave": "all.wav",
							"start": "04:36.097",
							"end": "04:41.449"
						},
						{
							"type": "A",
							"text": "네, 집으로 돌아가는 길이 매일 힘들어요.",
							"wave": "all.wav",
							"start": "04:42.638",
							"end": "04:45.598"
						}
					]
				},
				{
					"항목": "행복",
					"임상가코멘트": {
						"val": "④ 환경적 요인으로 인해 불행감을 느끼고 있으므로 사회복지적 측면에서 도움이 요구됩니다. [7점]"
					},
					"점수": 7,
					"행복감": {
						"val": "불행"
					},
					"불행통제": {
						"val": "통제 불가능한 요인"
					},
					"audio": [
						{
							"type": "Q",
							"text": "요즘 행복한 거 같나요, 불행한 거 같나요?",
							"wave": "all.wav",
							"start": "04:46.843",
							"end": "04:49.802"
						},
						{
							"type": "A",
							"text": "불행해요.",
							"wave": "all.wav",
							"start": "04:51.047",
							"end": "04:51.877"
						},
						{
							"type": "Q",
							"text": "왜 불행하다고 느껴요?",
							"wave": "all.wav",
							"start": "04:53.025",
							"end": "04:54.905"
						},
						{
							"type": "A",
							"text": "화목한 집에서 태어나지 못해서요.",
							"wave": "all.wav",
							"start": "04:56.164",
							"end": "04:58.736"
						}
					]
				},
				{
					"항목": "미래/진로",
					"임상가코멘트": {
						"val": "⑤ 개인적 요인(우울, 상실감 등)으로 미래에 대한 희망이 부재할 가능성 있음 [6점]"
					},
					"점수": 6,
					"미래진로": {
						"val": "장래희망/미래 없음"
					},
					"audio": [
						{
							"type": "Q",
							"text": "커서 어떤 사람이 되고 싶어요? 꿈이 뭔지 말해줄 수 있나요?",
							"wave": "all.wav",
							"start": "04:59.843",
							"end": "05:04.268"
						},
						{
							"type": "A",
							"text": "되고 싶은 게 없어요.",
							"wave": "all.wav",
							"start": "05:05.388",
							"end": "05:07.006"
						},
						{
							"type": "Q",
							"text": "하고 싶은 게 아예 없어요?",
							"wave": "all.wav",
							"start": "05:08.127",
							"end": "05:10.021"
						},
						{
							"type": "A",
							"text": "네, 맞고 사는데 무슨 꿈이 있겠어요.",
							"wave": "all.wav",
							"start": "05:11.114",
							"end": "05:14.032"
						}
					]
				}
			]
		},
		{
			"문항": "학대여부",
			"문항합계": 23,
			"위기단계": "학대의심",
			"list": [
				{
					"항목": "방임",
					"임상가코멘트": {
						"val": "④ 돌봄의 결핍/부재로 물리,정서적 필요를 충족하지 못하는 어려움이 발생 [8점]"
					},
					"점수": 8,
					"주양육자": {
						"val": "어머니"
					},
					"방임요인": {
						"val": "||보호자 참석 동행 없음||기타||",
						"기타": "병원에 데려가지 않음"
					},
					"audio": [
						{
							"type": "Q",
							"text": "집에서 주로 나를 돌봐주는 어른은 누구인가요? 학교, 학원이 끝나고 오면 항상 계시나요?",
							"wave": "all.wav",
							"start": "05:15.083",
							"end": "05:21.251"
						},
						{
							"type": "A",
							"text": "집에 있어도 안 돌봐주는 거 같아요.",
							"wave": "all.wav",
							"start": "05:22.357",
							"end": "05:24.695"
						},
						{
							"type": "Q",
							"text": "배가 고픈데 먹을 게 없어서 굶은 적이 있나요?",
							"wave": "all.wav",
							"start": "05:25.995",
							"end": "05:29.314"
						},
						{
							"type": "A",
							"text": "아니요.",
							"wave": "all.wav",
							"start": "05:30.434",
							"end": "05:31.291"
						},
						{
							"type": "Q",
							"text": "어디 아픈 곳이 있는데, 어른들이 나를 병원에 데려가지 않은 적이 있나요?",
							"wave": "all.wav",
							"start": "05:32.481",
							"end": "05:37.128"
						},
						{
							"type": "A",
							"text": "네, 엉덩이에 멍이 심하게 들었는데 병원에 데려가지 않았어요.",
							"wave": "all.wav",
							"start": "05:38.248",
							"end": "05:42.148"
						},
						{
							"type": "Q",
							"text": "빨래가 되지 않아서 더럽고 냄새나는 옷을 입어야 한 적이 있나요?",
							"wave": "all.wav",
							"start": "05:43.337",
							"end": "05:47.638"
						},
						{
							"type": "A",
							"text": "아니요.",
							"wave": "all.wav",
							"start": "05:48.606",
							"end": "05:49.547"
						},
						{
							"type": "Q",
							"text": "옷이나 신발 크기가 작은 걸 입거나 신고 다닌 적이 있나요?",
							"wave": "all.wav",
							"start": "05:50.487",
							"end": "05:54.512"
						},
						{
							"type": "A",
							"text": "아니요.",
							"wave": "all.wav",
							"start": "05:55.632",
							"end": "05:56.669"
						},
						{
							"type": "Q",
							"text": "인터넷이나 휴대전화를 가지고 노는 시간은 하루에 몇 시간 정도인가요?",
							"wave": "all.wav",
							"start": "05:57.858",
							"end": "06:02.505"
						},
						{
							"type": "A",
							"text": "휴대전화 없어요. 피시방에서는 한두 시간 있는 거 같아요.",
							"wave": "all.wav",
							"start": "06:03.542",
							"end": "06:07.456"
						},
						{
							"type": "Q",
							"text": "어른들이 운동회, 참관수업, 상담 등 학교 행사에 잘 오시나요?",
							"wave": "all.wav",
							"start": "06:08.604",
							"end": "06:13.555"
						},
						{
							"type": "A",
							"text": "아니요. 누나한테만 가고 저한텐 온 적이 없어요.",
							"wave": "all.wav",
							"start": "06:14.565",
							"end": "06:17.856"
						}
					]
				},
				{
					"항목": "정서학대",
					"임상가코멘트": {
						"val": "② 정서적 학대 의심으로 인하여 우울 또는 심리적 불편감을 경험할 수 있습니다. [5점]"
					},
					"점수": 5,
					"문제요인": {
						"val": "있음"
					},
					"대상": {
						"val": "||아버지||어머니||"
					},
					"학대유형": {
						"val": "||비난||"
					},
					"audio": [
						{
							"type": "Q",
							"text": "부모님이나 선생님 때문에 기분이 안 좋아진 적이 있나요?",
							"wave": "all.wav",
							"start": "06:19.018",
							"end": "06:23.139"
						},
						{
							"type": "A",
							"text": "네, 아빠랑 새엄마가 욕을 할 때 기분이 안 좋아요. 아빠는 항상 화날 때 욕설을 뱉고, 새엄마는 너네만 없었으면 좋은 집이 될 수 있었을 거라고 해요.",
							"wave": "all.wav",
							"start": "06:24.329",
							"end": "06:34.327"
						},
						{
							"type": "Q",
							"text": "내가 무엇을 하려고 하면 무조건 안 된다고 하거나, 하기 싫은 데 억지로 시킨 적이 있나요?",
							"wave": "all.wav",
							"start": "06:35.641",
							"end": "06:41.616"
						},
						{
							"type": "A",
							"text": "네, 집안일을 형이랑 제가 해야 해요.",
							"wave": "all.wav",
							"start": "06:42.694",
							"end": "06:45.654"
						},
						{
							"type": "Q",
							"text": "어른들이 나를 내쫓아 버리거나, 그런다고 하거나, 어디 가두고 못 나오게 한 적이 있나요?",
							"wave": "all.wav",
							"start": "06:46.871",
							"end": "06:52.527"
						},
						{
							"type": "A",
							"text": "네, 집에 발도 못 붙이게 하겠다고 한 적이 있어요.",
							"wave": "all.wav",
							"start": "06:53.786",
							"end": "06:57.119"
						},
						{
							"type": "Q",
							"text": "마음이 힘들 때, 가족에게 내 마음을 이야기하나요?",
							"wave": "all.wav",
							"start": "06:58.267",
							"end": "07:01.697"
						},
						{
							"type": "A",
							"text": "형이랑 이야기해요.",
							"wave": "all.wav",
							"start": "07:03.066",
							"end": "07:04.297"
						}
					]
				},
				{
					"항목": "신체학대",
					"임상가코멘트": {
						"val": "④ 심각한 수준의 체벌과 학대로 적극적인 대처가 필요한 것으로 보입니다. [10점]"
					},
					"점수": 10,
					"문제요인": {
						"val": "있음"
					},
					"이유": {
						"val": "비훈육"
					},
					"대상": {
						"val": "||아버지||"
					},
					"부위": {
						"val": "||엉덩이||"
					},
					"정도": {
						"val": "||통증||골절||"
					},
					"도구": {
						"val": "||비 훈육용 도구||"
					},
					"audio": [
						{
							"type": "Q",
							"text": "주위 어른이나 가족들 중 나를 때렸던 사람이 있나요?",
							"wave": "all.wav",
							"start": "07:05.500",
							"end": "07:09.400"
						},
						{
							"type": "A",
							"text": "네, 아빠가 때렸어요.",
							"wave": "all.wav",
							"start": "07:10.727",
							"end": "07:12.581"
						},
						{
							"type": "Q",
							"text": "아빠가 나를 왜 때리는 거 같아요?",
							"wave": "all.wav",
							"start": "07:13.728",
							"end": "07:16.342"
						},
						{
							"type": "A",
							"text": "화가 나서 때리는 거 같아요. 본인 기분에 따라서요.",
							"wave": "all.wav",
							"start": "07:17.615",
							"end": "07:21.113"
						},
						{
							"type": "Q",
							"text": "어느 부위를 무엇으로 맞나요? 그렇게 자주 때리나요?",
							"wave": "all.wav",
							"start": "07:22.358",
							"end": "07:25.871"
						},
						{
							"type": "A",
							"text": "주로 야구방망이로 엉덩이를 때려요. 일주일에 한 번 이상이요.",
							"wave": "all.wav",
							"start": "07:27.116",
							"end": "07:31.334"
						},
						{
							"type": "Q",
							"text": "맞은 것 때문에 다치거나 병원에 가서 치료받은 적이 있나요?",
							"wave": "all.wav",
							"start": "07:32.482",
							"end": "07:36.534"
						},
						{
							"type": "A",
							"text": "네, 있어요. 병원에 안 데려가서 학교 선생님이 데려갔어요. 꼬리뼈가 골절된 거 같다 그래서 병원에 다녀요.",
							"wave": "all.wav",
							"start": "07:37.557",
							"end": "07:44.762"
						}
					]
				},
				{
					"항목": "성학대",
					"임상가코멘트": {
						"val": "① 성적 학대의 징후가 유추되지 않습니다. [0점]"
					},
					"점수": 0,
					"문제요인": {
						"val": "없음"
					},
					"상황": {
						"val": "||"
					},
					"가해자": {
						"val": "||"
					},
					"성폭력유형": {
						"val": "||"
					},
					"audio": [
						{
							"type": "Q",
							"text": "누군가가 나의 몸을 만지려고 하거나 억지로 보려고 한 적이 있나요?",
							"wave": "all.wav",
							"start": "07:45.952",
							"end": "07:50.363"
						},
						{
							"type": "A",
							"text": "아니요.",
							"wave": "all.wav",
							"start": "07:51.580",
							"end": "07:52.396"
						},
						{
							"type": "Q",
							"text": "누군가가 나의 소중한 부위를 만지거나 아프게 한 적이 있나요?",
							"wave": "all.wav",
							"start": "07:53.447",
							"end": "07:57.264"
						},
						{
							"type": "A",
							"text": "아니요.",
							"wave": "all.wav",
							"start": "07:58.246",
							"end": "07:59.145"
						},
						{
							"type": "Q",
							"text": "혹시 나의 신체 부위의 사진, 영상을 찍어서 누구한테 보내거나 올린 적이 있어요?",
							"wave": "all.wav",
							"start": "08:00.169",
							"end": "08:05.604"
						},
						{
							"type": "A",
							"text": "아니요.",
							"wave": "all.wav",
							"start": "08:06.848",
							"end": "08:07.568"
						},
						{
							"type": "Q",
							"text": "그러면 그렇게 해달라고 한 사람이 있어요?",
							"wave": "all.wav",
							"start": "08:08.881",
							"end": "08:11.468"
						},
						{
							"type": "A",
							"text": "아니요.",
							"wave": "all.wav",
							"start": "08:12.422",
							"end": "08:13.182"
						},
						{
							"type": "Q",
							"text": "내가 싫다는 데 자꾸 따라다니거나 연락하는 사람이 있어요?",
							"wave": "all.wav",
							"start": "08:14.081",
							"end": "08:18.175"
						},
						{
							"type": "A",
							"text": "아니요.",
							"wave": "all.wav",
							"start": "08:19.198",
							"end": "08:20.153"
						}
					]
				}
			]
		},
		{
			"문항": "응급",
			"문항합계": 8,
			"위기단계": "위기아동",
			"list": [
				{
					"항목": "가정폭력",
					"임상가코멘트": {
						"val": "① 유의한 가정폭력 징후가 유추되지 않습니다. [0점]"
					},
					"점수": 0,
					"직접적 경험": {
						"val": "없음"
					},
					"간접적 경험": {
						"val": "없음"
					},
					"분리·격리조치 경험": {
						"val": "없음"
					},
					"신고경험": {
						"val": "없음"
					},
					"보호자 알코올·물질남용 중독": {
						"val": "(해당 없음)"
					},
					"audio": [
						{
							"type": "Q",
							"text": "가족들끼리 소리를 지르면서 싸우는 걸 듣거나 본 적이 있어요?",
							"wave": "all.wav",
							"start": "08:21.148",
							"end": "08:25.781"
						},
						{
							"type": "A",
							"text": "아니요. 없어요.",
							"wave": "all.wav",
							"start": "08:26.888",
							"end": "08:28.202"
						}
					]
				},
				{
					"항목": "학교폭력",
					"임상가코멘트": {
						"val": "① 학교 폭력의 징후가 유추되지 않습니다. [0점]"
					},
					"점수": 0,
					"문제요인": {
						"val": "없음"
					},
					"가해자": {
						"val": "||"
					},
					"반응": {
						"val": "||"
					},
					"폭력유형": {
						"val": "||"
					},
					"audio": [
						{
							"type": "Q",
							"text": "어른이 아닌 주변 사람들이 나를 자주 놀리거나 괴롭힌다고 느낀 적이 있나요?",
							"wave": "all.wav",
							"start": "08:29.432",
							"end": "08:34.660"
						},
						{
							"type": "A",
							"text": "아니요. 없어요.",
							"wave": "all.wav",
							"start": "08:35.753",
							"end": "08:37.094"
						}
					]
				},
				{
					"항목": "자해/자살",
					"임상가코멘트": {
						"val": "① 자해/자살의 징후가 유추되지 않습니다. [0점]"
					},
					"점수": 0,
					"자해욕구": {
						"val": "없음"
					},
					"자살욕구": {
						"val": "없음"
					},
					"유형": {
						"val": "(해당 없음)"
					},
					"audio": [
						{
							"type": "Q",
							"text": "어떨 때 마음이 복잡하고 힘들어요?",
							"wave": "all.wav",
							"start": "08:38.173",
							"end": "08:40.745"
						},
						{
							"type": "A",
							"text": "집으로 돌아가는 길에 마음이 복잡해요.",
							"wave": "all.wav",
							"start": "08:41.865",
							"end": "08:44.631"
						},
						{
							"type": "Q",
							"text": "안 좋은 기억 때문에 괴로워서 스스로 해치고 싶단 생각을 해본 적이 있나요?",
							"wave": "all.wav",
							"start": "08:45.876",
							"end": "08:50.951"
						},
						{
							"type": "A",
							"text": "아니요.",
							"wave": "all.wav",
							"start": "08:52.058",
							"end": "08:52.832"
						},
						{
							"type": "Q",
							"text": "그러면 혹시 죽고 싶다는 생각을 해본 적이 있나요?",
							"wave": "all.wav",
							"start": "08:53.925",
							"end": "08:57.410"
						},
						{
							"type": "A",
							"text": "아니요.",
							"wave": "all.wav",
							"start": "08:58.475",
							"end": "08:59.166"
						}
					]
				},
				{
					"항목": "트라우마",
					"임상가코멘트": {
						"val": "⑥ 외상 경험의 기억을 자주 떠올립니다. 적절한 심리적 개입이 요구됩니다. [8점]"
					},
					"점수": 8,
					"악몽여부": {
						"val": "있음"
					},
					"악몽내용": {
						"val": "||실제로 일어났던 일임||"
					},
					"신체상태": {
						"val": "이상 있음(식은땀, 가슴두근거림 등)"
					},
					"외상 재경험": {
						"val": "자주"
					},
					"audio": [
						{
							"type": "Q",
							"text": "잠잘 때 주로 어떤 꿈을 꾸나요? 악몽을 꾸나요?",
							"wave": "all.wav",
							"start": "09:00.204",
							"end": "09:03.467"
						},
						{
							"type": "A",
							"text": "아빠가 야구방망이를 들고 뛰어오던 게 꿈으로 나와요.",
							"wave": "all.wav",
							"start": "09:04.532",
							"end": "09:08.156"
						},
						{
							"type": "Q",
							"text": "잠에서 자주 깨는 이유가 무섭거나 끔찍한 경험 때문인가요? 어떤 기억 때문에 그래요?",
							"wave": "all.wav",
							"start": "09:09.221",
							"end": "09:15.237"
						},
						{
							"type": "A",
							"text": "아빠한테 맞던 기억이 떠올라서 그래요.",
							"wave": "all.wav",
							"start": "09:16.412",
							"end": "09:18.860"
						},
						{
							"type": "Q",
							"text": "꿈을 꾸고 일어나면 몸 상태가 어때요?",
							"wave": "all.wav",
							"start": "09:19.966",
							"end": "09:22.801"
						},
						{
							"type": "A",
							"text": "심장이 터질 거 같아요.",
							"wave": "all.wav",
							"start": "09:23.991",
							"end": "09:25.816"
						},
						{
							"type": "Q",
							"text": "생각하고 싶지 않은 데도 자꾸 안 좋은 기억이 떠오르나요? 일주일에 몇 번이나 그런가요?",
							"wave": "all.wav",
							"start": "09:26.826",
							"end": "09:32.496"
						},
						{
							"type": "A",
							"text": "매일 아빠한테 맞았던 기억과 맞을까 봐 걱정되는 생각이 들어요.",
							"wave": "all.wav",
							"start": "09:33.630",
							"end": "09:37.696"
						},
						{
							"type": "Q",
							"text": "이런 싫은 기억이 떠오를 때는 어떻게 하나요?",
							"wave": "all.wav",
							"start": "09:38.816",
							"end": "09:41.997"
						},
						{
							"type": "A",
							"text": "아빠랑 새엄마 죽으라고 저주해요.",
							"wave": "all.wav",
							"start": "09:43.325",
							"end": "09:45.745"
						}
					]
				},
				{
					"항목": "가출경험 및 가출중 정황",
					"임상가코멘트": {
						"val": "① 유의한 가출경험 징후가 유추되지 않습니다. [0점]"
					},
					"점수": 0,
					"가출경험": {
						"val": "없음"
					},
					"가출경험또래": {
						"val": "(해당 없음)"
					},
					"가출중사귄친구": {
						"val": "||"
					},
					"가출팸, 집단생활": {
						"val": "(해당 없음)"
					},
					"비행/범죄행동": {
						"val": "||"
					},
					"audio": [
						{
							"type": "Q",
							"text": "부모님의 허락 없이 또는 말도 없이 집에 오랫동안 나와 있었던 적이 있나요?",
							"wave": "all.wav",
							"start": "09:47.003",
							"end": "09:52.425"
						},
						{
							"type": "A",
							"text": "아니요.",
							"wave": "all.wav",
							"start": "09:53.476",
							"end": "09:54.306"
						},
						{
							"type": "Q",
							"text": "혹시 친구 중 가출한 친구가 있나요?",
							"wave": "all.wav",
							"start": "09:55.440",
							"end": "09:58.109"
						},
						{
							"type": "A",
							"text": "아니요. 없어요.",
							"wave": "all.wav",
							"start": "09:59.270",
							"end": "10:00.487"
						}
					]
				}
			]
		}
	]
}