{
	"version": 1,
	"info": {
		"ID": "3141",
		"성별": "남",
		"나이": 9,
		"학년": "저학년",
		"유형구분": "시설거주 아동",
		"가정환경": "시설거주",
		"상담일자": "2023-11-14",
		"평가일시": "2023-11-14",
		"작성자(상담사)": "임상심리사 2급",
		"상호작용 특성(종합)": "공격적",
		"긴장 수준(종합)": "보통",
		"행동 특성(종합)": "||",
		"위기단계": "정상군",
		"합계점수": 8,
		"학대의심": "(해당 없음)",
		"행동특성 점수": 0,
		"임상가 종합소견": "종합적 소견으로, 해당 아동은 신체 생리적 원인에 따른 신체적 통증을 경험하였을 가능성이 높으며, 신체적 손상에 관련된 문제는 나타나지 않았습니다. 긍정적 정서와 관련하여 건강하며, 분노와 짜증을 경험하고 있으나 적절한 대처기술이 있는 것으로 확인됩니다. 대인관계적 측면에서 어머니와 시설종사자, 친구의 관계에서는 건강하게 관계하고 있으나 교사에 대한 부정적 정서 경험을 나타냈습니다. 그러나 이는 개인적인 관계 양상으로 여겨집니다. 스트레스 수준이 낮고 긍정심리자원이 충분하여 정신건강의 문제는 유추되지 않으며, 적절한 돌봄을 받고 있고 학대나 폭력의 징후가 유추되지 않았습니다. 따라서, 해당 아동은 신체 및 심리적 문제가 발견되지 않았으나 아동의 건강한 성장 및 발전을 위해 꾸준히 관심을 두는 것은 필요합니다."
	},
	"list": [
		{
			"문항": "신체적 불편감",
			"문항합계": 3,
			"위기단계": "정상군",
			"list": [
				{
					"항목": "통증",
					"임상가코멘트": {
						"val": "② 통증이 신체 생리적 원인에 따른 것일 수 있습니다. [3점]"
					},
					"점수": 3,
					"문제요인": {
						"val": "있음"
					},
					"부위": {
						"val": "||소화불량||"
					},
					"빈도": {
						"val": "||처음||"
					},
					"기간": {
						"val": "||1주 미만||"
					},
					"audio": [
						{
							"type": "Q",
							"text": "최근에 건강하니 아니면 아픈 적이 있었어?",
							"wave": "all.wav",
							"start": "00:05.406",
							"end": "00:09.100"
						},
						{
							"type": "A",
							"text": "3일 전에 토했어요.",
							"wave": "all.wav",
							"start": "00:10.676",
							"end": "00:13.694"
						},
						{
							"type": "Q",
							"text": "아팠던 이유가 뭐였어? 지금도 아파?",
							"wave": "all.wav",
							"start": "00:15.676",
							"end": "00:19.325"
						},
						{
							"type": "A",
							"text": "병원에서 상한 음식을 먹어서 그렇다고 했어요. 지금은 안 아파요.",
							"wave": "all.wav",
							"start": "00:20.992",
							"end": "00:26.488"
						},
						{
							"type": "Q",
							"text": "일주일에 몇 번 정도 아팠어? 이전에도 자주 아팠어?",
							"wave": "all.wav",
							"start": "00:28.335",
							"end": "00:32.524"
						},
						{
							"type": "A",
							"text": "처음이었어요.",
							"wave": "all.wav",
							"start": "00:34.506",
							"end": "00:37.164"
						}
					]
				},
				{
					"항목": "신체손상",
					"임상가코멘트": {
						"val": "① 신체적 손상에 관련된 특별한 문제가 없어보입니다. [0점]"
					},
					"점수": 0,
					"문제요인": {
						"val": "없음"
					},
					"손상정도": {
						"val": "(해당 없음)"
					},
					"손상요인": {
						"val": "(해당 없음)"
					},
					"audio": [
						{
							"type": "Q",
							"text": "최근에 다친 적이 있었어?",
							"wave": "all.wav",
							"start": "00:39.056",
							"end": "00:42.119"
						},
						{
							"type": "A",
							"text": "없어요.",
							"wave": "all.wav",
							"start": "00:43.516",
							"end": "00:45.768"
						}
					]
				}
			]
		},
		{
			"문항": "기분문제",
			"문항합계": 3,
			"위기단계": "정상군",
			"list": [
				{
					"항목": "즐거움",
					"임상가코멘트": {
						"val": "① 긍정적 정서와 관련하여 건강한 상태로 여겨집니다. [0점]"
					},
					"점수": 0,
					"문제요인": {
						"val": "없음"
					},
					"지속시간": {
						"val": "(해당 없음)"
					},
					"audio": [
						{
							"type": "Q",
							"text": "친구는 뭘 할 때가 즐거워?",
							"wave": "all.wav",
							"start": "00:47.660",
							"end": "00:50.678"
						},
						{
							"type": "A",
							"text": "저는 축구할 때 제일 즐거워요.",
							"wave": "all.wav",
							"start": "00:52.795",
							"end": "00:56.264"
						},
						{
							"type": "Q",
							"text": "어떤 부분이 즐거워?",
							"wave": "all.wav",
							"start": "00:57.886",
							"end": "01:00.724"
						},
						{
							"type": "A",
							"text": "달리고 골 넣으면 신나니까요.",
							"wave": "all.wav",
							"start": "01:02.345",
							"end": "01:05.814"
						}
					]
				},
				{
					"항목": "분노/짜증",
					"임상가코멘트": {
						"val": "② 분노와 짜증을 경험하지만 적절한 대처기술이 있습니다. [3점]"
					},
					"점수": 3,
					"문제요인": {
						"val": "||짜증||"
					},
					"대처기술": {
						"val": "있음"
					},
					"audio": [
						{
							"type": "Q",
							"text": "최근 일주일 동안 짜증이나 화가 난 적이 있어?",
							"wave": "all.wav",
							"start": "01:08.112",
							"end": "01:12.346"
						},
						{
							"type": "A",
							"text": "짜증 났어요.",
							"wave": "all.wav",
							"start": "01:14.013",
							"end": "01:16.400"
						},
						{
							"type": "Q",
							"text": "무엇 때문에 짜증이 났어?",
							"wave": "all.wav",
							"start": "01:18.202",
							"end": "01:20.770"
						},
						{
							"type": "A",
							"text": "센터에 별로 안 좋아하는 애가 있는데 걔가 시비 걸어서요.",
							"wave": "all.wav",
							"start": "01:22.797",
							"end": "01:27.977"
						},
						{
							"type": "Q",
							"text": "그런 일이 자주 일어나?",
							"wave": "all.wav",
							"start": "01:30.185",
							"end": "01:33.068"
						},
						{
							"type": "A",
							"text": "그건 아니에요.",
							"wave": "all.wav",
							"start": "01:35.095",
							"end": "01:37.753"
						},
						{
							"type": "Q",
							"text": "평소에 짜증이나 화가 났을 때 어떻게 하면 마음이 풀려?",
							"wave": "all.wav",
							"start": "01:39.329",
							"end": "01:44.645"
						},
						{
							"type": "A",
							"text": "축구하러 가거나 배드민턴 해요.",
							"wave": "all.wav",
							"start": "01:46.041",
							"end": "01:49.600"
						}
					]
				}
			]
		},
		{
			"문항": "자율신경계",
			"문항합계": 0,
			"위기단계": "정상군",
			"list": [
				{
					"항목": "수면",
					"임상가코멘트": {
						"val": "① 신체·생리적으로 건강한 상태인 것으로 여겨집니다. [0점]"
					},
					"점수": 0,
					"수면시간": {
						"val": "9"
					},
					"문제요인": {
						"val": "없음"
					},
					"수면문제": {
						"val": "||"
					},
					"audio": [
						{
							"type": "Q",
							"text": "보통 몇 시에 자고 몇 시에 일어나?",
							"wave": "all.wav",
							"start": "01:51.672",
							"end": "01:55.501"
						},
						{
							"type": "A",
							"text": "열 시에 자서 일곱 시에 일어나요.",
							"wave": "all.wav",
							"start": "01:57.889",
							"end": "02:01.673"
						},
						{
							"type": "Q",
							"text": "아침에 일어났을 때 몸 상태는 어때?",
							"wave": "all.wav",
							"start": "02:03.430",
							"end": "02:07.484"
						},
						{
							"type": "A",
							"text": "괜찮아요.",
							"wave": "all.wav",
							"start": "02:09.421",
							"end": "02:11.808"
						},
						{
							"type": "Q",
							"text": "평소에 잠이 들기 힘들거나, 잠자는 중간에 자주 깨는 경우가 있어?",
							"wave": "all.wav",
							"start": "02:13.745",
							"end": "02:18.971"
						},
						{
							"type": "A",
							"text": "안 깨요.",
							"wave": "all.wav",
							"start": "02:20.593",
							"end": "02:23.160"
						}
					]
				}
			]
		},
		{
			"문항": "대인관계",
			"문항합계": 2,
			"위기단계": "정상군",
			"list": [
				{
					"항목": "아버지",
					"임상가코멘트": {
						"val": ""
					},
					"점수": 0,
					"아버지": {
						"val": "안계심"
					},
					"대상자": {
						"val": "(해당 없음)"
					},
					"관계": {
						"val": "(해당 없음)"
					},
					"차별": {
						"val": "(해당 없음)"
					},
					"audio": [
						{
							"type": "Q",
							"text": "평소에 아버지는 어떤 표정을 자주 지으셔?",
							"wave": "all.wav",
							"start": "02:24.917",
							"end": "02:28.926"
						},
						{
							"type": "A",
							"text": "아빠는 어릴 때 돌아가셨다고 했어요.",
							"wave": "all.wav",
							"start": "02:31.539",
							"end": "02:35.638"
						}
					]
				},
				{
					"항목": "어머니",
					"임상가코멘트": {
						"val": "① 건강한 관계를 형성하고 있는 것으로 보입니다. [0점]"
					},
					"점수": 0,
					"어머니": {
						"val": "우호"
					},
					"대상자": {
						"val": "(해당 없음)"
					},
					"관계": {
						"val": "(해당 없음)"
					},
					"차별": {
						"val": "(해당 없음)"
					},
					"audio": [
						{
							"type": "Q",
							"text": "평소에 어머니는 어떤 표정을 자주 지으셔?",
							"wave": "all.wav",
							"start": "02:37.575",
							"end": "02:41.540"
						},
						{
							"type": "A",
							"text": "센터에 올 때만 보는데, 항상 웃어요.",
							"wave": "all.wav",
							"start": "02:43.387",
							"end": "02:47.306"
						},
						{
							"type": "Q",
							"text": "어머니께서 그런 표정을 짓는 이유가 뭘까?",
							"wave": "all.wav",
							"start": "02:49.063",
							"end": "02:52.846"
						},
						{
							"type": "A",
							"text": "좋아서 그런 것 같아요.",
							"wave": "all.wav",
							"start": "02:55.189",
							"end": "02:58.387"
						},
						{
							"type": "Q",
							"text": "그 표정을 지을 때, 친구 기분은 어때?",
							"wave": "all.wav",
							"start": "03:00.414",
							"end": "03:04.469"
						},
						{
							"type": "A",
							"text": "좋은 것 같아요.",
							"wave": "all.wav",
							"start": "03:06.631",
							"end": "03:09.018"
						}
					]
				},
				{
					"항목": "기타 보호자",
					"임상가코멘트": {
						"val": "① 건강한 관계를 형성하고 있는 것으로 보입니다. [0점]"
					},
					"점수": 0,
					"기타보호자명": {
						"이름입력": "시설종사자",
						"val": "우호"
					},
					"대상자": {
						"val": "(해당 없음)"
					},
					"관계": {
						"val": "(해당 없음)"
					},
					"차별": {
						"val": "(해당 없음)"
					},
					"audio": [
						{
							"type": "Q",
							"text": "평소 시설 선생님은 어떤 표정을 자주 지으셔?",
							"wave": "all.wav",
							"start": "03:11.181",
							"end": "03:16.181"
						},
						{
							"type": "A",
							"text": "웃는 표정요.",
							"wave": "all.wav",
							"start": "03:18.478",
							"end": "03:21.406"
						},
						{
							"type": "Q",
							"text": "그런 표정을 짓는 이유가 뭘까?",
							"wave": "all.wav",
							"start": "03:23.524",
							"end": "03:27.173"
						},
						{
							"type": "A",
							"text": "저희가 좋아서요.",
							"wave": "all.wav",
							"start": "03:29.155",
							"end": "03:31.902"
						},
						{
							"type": "Q",
							"text": "그 표정을 지을 때, 친구 기분은 어때?",
							"wave": "all.wav",
							"start": "03:34.020",
							"end": "03:38.074"
						},
						{
							"type": "A",
							"text": "나쁘지 않아요.",
							"wave": "all.wav",
							"start": "03:39.786",
							"end": "03:42.669"
						}
					]
				},
				{
					"항목": "형제자매",
					"임상가코멘트": {
						"val": ""
					},
					"점수": 0,
					"인원": {
						"val": "0"
					},
					"대상자": {
						"val": "(해당 없음)"
					},
					"관계": {
						"val": "(해당 없음)"
					},
					"차별": {
						"val": "(해당 없음)"
					}
				},
				{
					"항목": "친구",
					"임상가코멘트": {
						"val": "① 교우관계과 원만한 것으로 보입니다. [0점]"
					},
					"점수": 0,
					"문제요인": {
						"val": "없음"
					},
					"교우관계": {
						"val": "(해당 없음)"
					},
					"audio": [
						{
							"type": "Q",
							"text": "친구들이랑은 주로 뭐 하고 놀아?",
							"wave": "all.wav",
							"start": "03:45.507",
							"end": "03:49.516"
						},
						{
							"type": "A",
							"text": "축구해요.",
							"wave": "all.wav",
							"start": "03:51.318",
							"end": "03:53.615"
						},
						{
							"type": "Q",
							"text": "주로 몇 명에서 놀아?",
							"wave": "all.wav",
							"start": "03:55.597",
							"end": "03:58.480"
						},
						{
							"type": "A",
							"text": "학교나 센터나 다 같이 해요.",
							"wave": "all.wav",
							"start": "04:00.688",
							"end": "04:04.246"
						}
					]
				},
				{
					"항목": "교사",
					"임상가코멘트": {
						"val": "② 선생님에 대한 부정적 정서 경험을 나타내고 있으나 개인적 관계 양상인 것으로 여겨집니다. [2점]"
					},
					"점수": 2,
					"담임": {
						"val": "통제지배"
					},
					"audio": [
						{
							"type": "Q",
							"text": "담임 선생님은 좋아 싫어?",
							"wave": "all.wav",
							"start": "04:06.769",
							"end": "04:10.058"
						},
						{
							"type": "A",
							"text": "숙제도 많이 내주고 쪽지시험도 많이 쳐서 싫어요.",
							"wave": "all.wav",
							"start": "04:11.814",
							"end": "04:16.679"
						}
					]
				}
			]
		},
		{
			"문항": "기본생활",
			"문항합계": 0,
			"위기단계": "정상군",
			"list": [
				{
					"항목": "걱정",
					"임상가코멘트": {
						"val": "① 스트레스 수준이 낮아 정신건강의 문제가 유추되지 않습니다. [0점]"
					},
					"점수": 0,
					"내용": {
						"val": "걱정거리 없음"
					},
					"일상영향": {
						"val": "(해당 없음)"
					},
					"audio": [
						{
							"type": "Q",
							"text": "요즘 가장 큰 걱정거리는 어떤 거야?",
							"wave": "all.wav",
							"start": "04:19.157",
							"end": "04:23.166"
						},
						{
							"type": "A",
							"text": "저는 걱정거리 없는데요.",
							"wave": "all.wav",
							"start": "04:25.464",
							"end": "04:29.203"
						}
					]
				},
				{
					"항목": "행복",
					"임상가코멘트": {
						"val": "① 긍정심리자원(자아탄력성 등)이 충분 [0점]"
					},
					"점수": 0,
					"행복감": {
						"val": "행복"
					},
					"불행통제": {
						"val": "(해당 없음)"
					},
					"audio": [
						{
							"type": "Q",
							"text": "요즘에 행복하다고 느껴?",
							"wave": "all.wav",
							"start": "04:32.536",
							"end": "04:35.419"
						},
						{
							"type": "A",
							"text": "네. 행복해요.",
							"wave": "all.wav",
							"start": "04:37.762",
							"end": "04:40.014"
						},
						{
							"type": "Q",
							"text": "어떤 점에서 그렇게 느껴?",
							"wave": "all.wav",
							"start": "04:41.951",
							"end": "04:45.375"
						},
						{
							"type": "A",
							"text": "그냥 싫은 게 없어요.",
							"wave": "all.wav",
							"start": "04:47.672",
							"end": "04:50.645"
						}
					]
				},
				{
					"항목": "미래/진로",
					"임상가코멘트": {
						"val": "① 미래에 대한 희망적 요인(꿈/진로)이 긍정적인 자원으로 기능할 것으로 보입니다 [0점]"
					},
					"점수": 0,
					"미래진로": {
						"val": "긍정적 미래"
					},
					"audio": [
						{
							"type": "Q",
							"text": "커서 어떤 사람이 되고 싶어? 꿈이 있어?",
							"wave": "all.wav",
							"start": "04:52.898",
							"end": "04:57.357"
						},
						{
							"type": "A",
							"text": "축구선수나 배드민턴 선수요.",
							"wave": "all.wav",
							"start": "04:59.204",
							"end": "05:02.898"
						},
						{
							"type": "Q",
							"text": "되고 싶은 이유가 있어?",
							"wave": "all.wav",
							"start": "05:04.610",
							"end": "05:07.358"
						},
						{
							"type": "A",
							"text": "제일 좋아하는 운동이라서요.",
							"wave": "all.wav",
							"start": "05:09.610",
							"end": "05:13.124"
						}
					]
				}
			]
		},
		{
			"문항": "학대여부",
			"문항합계": 0,
			"위기단계": "",
			"list": [
				{
					"항목": "방임",
					"임상가코멘트": {
						"val": "① 적절한 돌봄을 받고 있는 것으로 여겨집니다. [0점]"
					},
					"점수": 0,
					"주양육자": {
						"val": "시설종사자"
					},
					"방임요인": {
						"val": "||"
					},
					"audio": [
						{
							"type": "Q",
							"text": "주로 나를 돌봐주는 어른은 누구셔?",
							"wave": "all.wav",
							"start": "05:16.052",
							"end": "05:19.746"
						},
						{
							"type": "A",
							"text": "예전에는 엄마고 지금은 센터 선생님이요.",
							"wave": "all.wav",
							"start": "05:21.458",
							"end": "05:26.233"
						},
						{
							"type": "Q",
							"text": "배가 고픈데 먹을 게 없어서 굶은 적이 있어?",
							"wave": "all.wav",
							"start": "05:29.025",
							"end": "05:33.170"
						},
						{
							"type": "A",
							"text": "없어요.",
							"wave": "all.wav",
							"start": "05:34.701",
							"end": "05:37.089"
						},
						{
							"type": "Q",
							"text": "아픈 곳이 있는데 어른들이 병원에 데려가지 않은 적이 있어?",
							"wave": "all.wav",
							"start": "05:39.927",
							"end": "05:44.702"
						},
						{
							"type": "A",
							"text": "아니요.",
							"wave": "all.wav",
							"start": "05:46.864",
							"end": "05:49.387"
						},
						{
							"type": "Q",
							"text": "더럽고 냄새나는 옷을 입어야 한 적이 있거나 작은 옷이나 신발을 신고 다닌 적이 있어?",
							"wave": "all.wav",
							"start": "05:51.414",
							"end": "05:57.676"
						},
						{
							"type": "A",
							"text": "없는데요.",
							"wave": "all.wav",
							"start": "05:59.522",
							"end": "06:02.225"
						},
						{
							"type": "Q",
							"text": "휴대폰을 하는 시간은 하루에 몇 시간 정도야?",
							"wave": "all.wav",
							"start": "06:04.162",
							"end": "06:08.127"
						},
						{
							"type": "A",
							"text": "세 시간이요.",
							"wave": "all.wav",
							"start": "06:10.199",
							"end": "06:12.046"
						},
						{
							"type": "Q",
							"text": "많이 한다고 뭐라 하시진 않아?",
							"wave": "all.wav",
							"start": "06:14.253",
							"end": "06:17.361"
						},
						{
							"type": "A",
							"text": "뭐라고 하죠. 그러면 그만 해요.",
							"wave": "all.wav",
							"start": "06:19.929",
							"end": "06:23.578"
						},
						{
							"type": "Q",
							"text": "어른들이 운동회나 참관 수업, 학부모 상담 같은 학교 행사에 잘 오셔?",
							"wave": "all.wav",
							"start": "06:25.695",
							"end": "06:31.236"
						},
						{
							"type": "A",
							"text": "엄마가 거의 오고, 엄마가 못 오면 센터 선생님이 와요.",
							"wave": "all.wav",
							"start": "06:33.173",
							"end": "06:38.038"
						}
					]
				},
				{
					"항목": "정서학대",
					"임상가코멘트": {
						"val": "① 정서적 학대의 징후가 유추되지 않습니다. [0점]"
					},
					"점수": 0,
					"문제요인": {
						"val": "없음"
					},
					"대상": {
						"val": "||"
					},
					"학대유형": {
						"val": "||"
					},
					"audio": [
						{
							"type": "Q",
							"text": "주변 어른들 때문에 기분이 안 좋아진 적이 있어?",
							"wave": "all.wav",
							"start": "06:40.425",
							"end": "06:45.020"
						},
						{
							"type": "A",
							"text": "없어요.",
							"wave": "all.wav",
							"start": "06:46.687",
							"end": "06:48.669"
						},
						{
							"type": "Q",
							"text": "친구가 뭘 할 때, 무조건 안 된다고 하거나, 무조건 하라고 할 때가 있어?",
							"wave": "all.wav",
							"start": "06:50.561",
							"end": "06:55.741"
						},
						{
							"type": "A",
							"text": "아니요.",
							"wave": "all.wav",
							"start": "06:57.228",
							"end": "06:59.616"
						},
						{
							"type": "Q",
							"text": "어른들이 집에서 쫓아내거나 버리겠다고 말하거나, 어디에 가두고 못 나오게 한 적이 있어?",
							"wave": "all.wav",
							"start": "07:01.417",
							"end": "07:07.769"
						},
						{
							"type": "A",
							"text": "이런 거 왜 물어요? 뉴스 같은데 말하려고요? 없는데요.",
							"wave": "all.wav",
							"start": "07:10.157",
							"end": "07:15.202"
						},
						{
							"type": "Q",
							"text": "마음이 힘들 때, 누구에게 이야기하는 편이야?",
							"wave": "all.wav",
							"start": "07:17.184",
							"end": "07:21.689"
						},
						{
							"type": "A",
							"text": "엄마요.",
							"wave": "all.wav",
							"start": "07:23.581",
							"end": "07:25.428"
						}
					]
				},
				{
					"항목": "신체학대",
					"임상가코멘트": {
						"val": "① 신체적 학대의 징후가 유추되지 않습니다. [0점]"
					},
					"점수": 0,
					"문제요인": {
						"val": "없음"
					},
					"이유": {
						"val": "(해당 없음)"
					},
					"대상": {
						"val": "||"
					},
					"부위": {
						"val": "||"
					},
					"정도": {
						"val": "||"
					},
					"도구": {
						"val": "||"
					},
					"audio": [
						{
							"type": "Q",
							"text": "주위 어른들 중 친구를 때린 사람이 있었어?",
							"wave": "all.wav",
							"start": "07:27.635",
							"end": "07:31.419"
						},
						{
							"type": "A",
							"text": "없어요.",
							"wave": "all.wav",
							"start": "07:32.996",
							"end": "07:35.248"
						},
						{
							"type": "Q",
							"text": "혼날 때는 주로 어떻게 혼나?",
							"wave": "all.wav",
							"start": "07:37.545",
							"end": "07:40.744"
						},
						{
							"type": "A",
							"text": "원장님이 부르시거나 반성문 써요.",
							"wave": "all.wav",
							"start": "07:43.041",
							"end": "07:47.366"
						}
					]
				},
				{
					"항목": "성학대",
					"임상가코멘트": {
						"val": "① 성적 학대의 징후가 유추되지 않습니다. [0점]"
					},
					"점수": 0,
					"문제요인": {
						"val": "없음"
					},
					"상황": {
						"val": "||"
					},
					"가해자": {
						"val": "||"
					},
					"성폭력유형": {
						"val": "||"
					},
					"audio": [
						{
							"type": "Q",
							"text": "조금 예민한 질문인데, 친구가 원하지 않는데도 누군가 친구 몸을 만지거나 보여달라고 한 적 있었어?",
							"wave": "all.wav",
							"start": "07:49.753",
							"end": "07:57.997"
						},
						{
							"type": "A",
							"text": "이런 거 짜증 나요. 없어요.",
							"wave": "all.wav",
							"start": "08:00.610",
							"end": "08:04.303"
						},
						{
							"type": "Q",
							"text": "혹시 친구의 신체 부위를 사진이나 영상으로 찍은 적이 있어?",
							"wave": "all.wav",
							"start": "08:06.150",
							"end": "08:11.871"
						},
						{
							"type": "A",
							"text": "없다니까요.",
							"wave": "all.wav",
							"start": "08:14.800",
							"end": "08:17.863"
						},
						{
							"type": "Q",
							"text": "친구가 싫다고 하는데도 계속해서 연락하거나 따라다니는 사람이 있어?",
							"wave": "all.wav",
							"start": "08:20.160",
							"end": "08:25.476"
						},
						{
							"type": "A",
							"text": "없어요. 그만 물어보세요.",
							"wave": "all.wav",
							"start": "08:27.683",
							"end": "08:31.332"
						}
					]
				}
			]
		},
		{
			"문항": "응급",
			"문항합계": 0,
			"위기단계": "",
			"list": [
				{
					"항목": "가정폭력",
					"임상가코멘트": {
						"val": "① 유의한 가정폭력 징후가 유추되지 않습니다. [0점]"
					},
					"점수": 0,
					"직접적 경험": {
						"val": "없음"
					},
					"간접적 경험": {
						"val": "없음"
					},
					"분리·격리조치 경험": {
						"val": "없음"
					},
					"신고경험": {
						"val": "없음"
					},
					"보호자 알코올·물질남용 중독": {
						"val": "(해당 없음)"
					},
					"audio": [
						{
							"type": "Q",
							"text": "집에서 어른들끼리 소리 지르면서 싸우는 걸 듣거나 본 적이 있어?",
							"wave": "all.wav",
							"start": "08:33.674",
							"end": "08:39.530"
						},
						{
							"type": "A",
							"text": "없어요.",
							"wave": "all.wav",
							"start": "08:41.152",
							"end": "08:43.044"
						},
						{
							"type": "Q",
							"text": "평상시에 어른들이 술을 마시고 집에서 무섭게 행동할 때가 많아?",
							"wave": "all.wav",
							"start": "08:44.711",
							"end": "08:49.531"
						},
						{
							"type": "A",
							"text": "아니요.",
							"wave": "all.wav",
							"start": "08:51.828",
							"end": "08:54.036"
						}
					]
				},
				{
					"항목": "학교폭력",
					"임상가코멘트": {
						"val": "① 학교 폭력의 징후가 유추되지 않습니다. [0점]"
					},
					"점수": 0,
					"문제요인": {
						"val": "없음"
					},
					"가해자": {
						"val": "||"
					},
					"반응": {
						"val": "||"
					},
					"폭력유형": {
						"val": "||"
					},
					"audio": [
						{
							"type": "Q",
							"text": "친구나 또래가 나를 자주 놀리거나 괴롭힌다고 느낀 적이 있어?",
							"wave": "all.wav",
							"start": "08:55.747",
							"end": "09:00.883"
						},
						{
							"type": "A",
							"text": "아니요.",
							"wave": "all.wav",
							"start": "09:02.234",
							"end": "09:04.802"
						}
					]
				},
				{
					"항목": "자해/자살",
					"임상가코멘트": {
						"val": "① 자해/자살의 징후가 유추되지 않습니다. [0점]"
					},
					"점수": 0,
					"자해욕구": {
						"val": "없음"
					},
					"자살욕구": {
						"val": "없음"
					},
					"유형": {
						"val": "(해당 없음)"
					},
					"audio": [
						{
							"type": "Q",
							"text": "어떨 때 마음이 복잡하거나 힘들어?",
							"wave": "all.wav",
							"start": "09:06.289",
							"end": "09:09.937"
						},
						{
							"type": "A",
							"text": "그런 적 없어요.",
							"wave": "all.wav",
							"start": "09:12.145",
							"end": "09:15.163"
						},
						{
							"type": "Q",
							"text": "안 좋은 기억 때문에 괴로워서 스스로를 해치거나 죽고 싶다는 생각을 한 적 있어?",
							"wave": "all.wav",
							"start": "09:17.776",
							"end": "09:24.488"
						},
						{
							"type": "A",
							"text": "아니요.",
							"wave": "all.wav",
							"start": "09:26.290",
							"end": "09:28.587"
						}
					]
				},
				{
					"항목": "트라우마",
					"임상가코멘트": {
						"val": "① 유의한 외상의 징후가 유추되지 않습니다. [0점]"
					},
					"점수": 0,
					"악몽여부": {
						"val": "없음"
					},
					"악몽내용": {
						"val": "||"
					},
					"신체상태": {
						"val": "(해당 없음)"
					},
					"외상 재경험": {
						"val": "없음"
					},
					"audio": [
						{
							"type": "Q",
							"text": "잠잘 때 주로 어떤 꿈을 꿔?",
							"wave": "all.wav",
							"start": "09:30.794",
							"end": "09:33.993"
						},
						{
							"type": "A",
							"text": "괴물 무찌르는 꿈이요.",
							"wave": "all.wav",
							"start": "09:36.695",
							"end": "09:40.119"
						},
						{
							"type": "Q",
							"text": "그런 꿈을 꾸는 이유가 무섭거나 끔찍하거나 힘들었던 경험 때문이야?",
							"wave": "all.wav",
							"start": "09:42.326",
							"end": "09:48.228"
						},
						{
							"type": "A",
							"text": "아니요. 멋진 꿈인데요.",
							"wave": "all.wav",
							"start": "09:49.849",
							"end": "09:53.408"
						},
						{
							"type": "Q",
							"text": "꿈을 꾸고 일어나면 몸 상태가 어때?",
							"wave": "all.wav",
							"start": "09:55.931",
							"end": "09:59.715"
						},
						{
							"type": "A",
							"text": "아무렇지도 않아요.",
							"wave": "all.wav",
							"start": "10:01.562",
							"end": "10:04.805"
						},
						{
							"type": "Q",
							"text": "생각하고 싶지 않은 데도 자꾸 안 좋은 기억이 떠오른 적이 있어?",
							"wave": "all.wav",
							"start": "10:07.328",
							"end": "10:12.148"
						},
						{
							"type": "A",
							"text": "없다니까요.",
							"wave": "all.wav",
							"start": "10:14.760",
							"end": "10:17.463"
						}
					]
				},
				{
					"항목": "가출경험 및 가출중 정황",
					"임상가코멘트": {
						"val": "① 유의한 가출경험 징후가 유추되지 않습니다. [0점]"
					},
					"점수": 0,
					"가출경험": {
						"val": "없음"
					},
					"가출경험또래": {
						"val": "없음"
					},
					"가출중사귄친구": {
						"val": "||"
					},
					"가출팸, 집단생활": {
						"val": "(해당 없음)"
					},
					"비행/범죄행동": {
						"val": "||"
					},
					"audio": [
						{
							"type": "Q",
							"text": "어른들 허락이나 말도 없이 집에 오랫동안 나와 있었던 적이 있었어?",
							"wave": "all.wav",
							"start": "10:19.626",
							"end": "10:25.347"
						},
						{
							"type": "A",
							"text": "가출 안 해요.",
							"wave": "all.wav",
							"start": "10:26.833",
							"end": "10:29.581"
						},
						{
							"type": "Q",
							"text": "친한 친구 중에 가출한 친구가 있어?",
							"wave": "all.wav",
							"start": "10:31.473",
							"end": "10:35.167"
						},
						{
							"type": "A",
							"text": "아니요.",
							"wave": "all.wav",
							"start": "10:36.744",
							"end": "10:38.636"
						}
					]
				}
			]
		}
	]
}